leap_ie/__init__.cp39-win_arm64.pyd
leap_ie/env.cp39-win_arm64.pyd
leap_ie/common_utils/__init__.cp39-win_arm64.pyd
leap_ie/common_utils/config.cp39-win_arm64.pyd
leap_ie/common_utils/console.cp39-win_arm64.pyd
leap_ie/common_utils/event_handler.cp39-win_arm64.pyd
leap_ie/common_utils/license.cp39-win_arm64.pyd
leap_ie/common_utils/logging_handler.cp39-win_arm64.pyd
leap_ie/common_utils/lr_finder.cp39-win_arm64.pyd
leap_ie/common_utils/monitoring.cp39-win_arm64.pyd
leap_ie/common_utils/requirements.cp39-win_arm64.pyd
leap_ie/common_utils/utils.cp39-win_arm64.pyd
leap_ie/common_utils/utils_pt.cp39-win_arm64.pyd
leap_ie/common_utils/utils_tf.cp39-win_arm64.pyd
leap_ie/common_utils/validate_input.cp39-win_arm64.pyd
leap_ie/vision/__init__.cp39-win_arm64.pyd
leap_ie/vision/class_lists.cp39-win_arm64.pyd
leap_ie/vision/engine.cp39-win_arm64.pyd
leap_ie/vision/generation.cp39-win_arm64.pyd
leap_ie/vision/generation_tf.cp39-win_arm64.pyd
leap_ie/vision/models.cp39-win_arm64.pyd
leap_ie/vision/models_pt.cp39-win_arm64.pyd
leap_ie/vision/models_tf.cp39-win_arm64.pyd
leap_ie/vision/objectives.cp39-win_arm64.pyd
leap_ie/vision/objectives_tf.cp39-win_arm64.pyd
leap_ie/vision/saliency.cp39-win_arm64.pyd
leap_ie/vision/saliency_tf.cp39-win_arm64.pyd
leap_ie/vision/transforms.cp39-win_arm64.pyd
leap_ie/vision/transforms_tf.cp39-win_arm64.pyd
leap_ie/vision/vega_charts.cp39-win_arm64.pyd
leap_ie-0.3.2.dist-info/LICENSE
leap_ie-0.3.2.dist-info/METADATA
leap_ie-0.3.2.dist-info/WHEEL
leap_ie-0.3.2.dist-info/top_level.txt
leap_ie-0.3.2.dist-info/RECORD
