Metadata-Version: 2.1
Name: leap_ie
Version: 0.3.2
Summary: Leap Labs Interpretability Engine
Home-page: https://www.leap-labs.com/
Author: Jessica Rumbelow
Author-email: jessica@leap-labs.com
License: Proprietary
Requires-Python: >=3.8
License-File: leap_ie/LICENSE
Requires-Dist: ipython >=7.23.1
Requires-Dist: pandas >=1.4.4
Requires-Dist: tqdm >=4.42.1
Requires-Dist: wandb >=0.15.4
Requires-Dist: numpy >=1.19.5
Requires-Dist: transformers >=4.30.2
Requires-Dist: matplotlib >=3.3.4
Requires-Dist: sentry-sdk >=1.37.1
Requires-Dist: python-dotenv >=1.0.0
Provides-Extra: with-tensorflow
Requires-Dist: tensorflow >=2.4.0 ; extra == 'with-tensorflow'
Requires-Dist: tensorflow-macos >=2.5.0 ; (platform_system == "Darwin") and extra == 'with-tensorflow'
Provides-Extra: with-torch
Requires-Dist: torch >=1.13.0 ; extra == 'with-torch'
Requires-Dist: torchvision >=0.14.0 ; extra == 'with-torch'
Requires-Dist: timm >=0.9.12 ; extra == 'with-torch'
